Metadata-Version: 2.1
Name: pyproxies
Version: 0.1
Summary: Python proxy scraper module, only returns valid proxies whose timeout is less than 10 seconds.
Home-page: https://github.com/venaxyt/pyproxies
Author: Venax
Author-email: venaxumofficial@gmail.com
License: MIT
Keywords: pyproxies
Platform: UNKNOWN
Classifier: Development Status :: 5 - Production/Stable
Classifier: Intended Audience :: Education
Classifier: Operating System :: Microsoft :: Windows :: Windows 10
Classifier: License :: OSI Approved :: MIT License
Classifier: Programming Language :: Python :: 3.9
